{
    "cardano-node": {
        "branch": "1.17.0",
        "description": null,
        "homepage": null,
        "owner": "input-output-hk",
        "repo": "cardano-node",
        "rev": "0191ff56d194b6ac074af0d51e67493c14e08ffa",
        "sha256": "1mwx751w6f59bhf8r4n72s0gy0fz5w4ss5jcds0fs8nvjlk7y3c6",
        "type": "tarball",
        "url": "https://github.com/input-output-hk/cardano-node/archive/0191ff56d194b6ac074af0d51e67493c14e08ffa.tar.gz",
        "url_template": "https://github.com/<owner>/<repo>/archive/<rev>.tar.gz"
    },
    "haskell.nix": {
        "branch": "master",
        "description": "Alternative Haskell Infrastructure for Nixpkgs",
        "homepage": "https://input-output-hk.github.io/haskell.nix",
        "owner": "input-output-hk",
        "repo": "haskell.nix",
        "rev": "aa33b830162a5025fea684ab8659778ea871ba67",
        "sha256": "0krx5hnmrxhka7bfmp6iaw9rm3shwg4bsh0kxhmv6jkw9sm7cxzm",
        "type": "tarball",
        "url": "https://github.com/input-output-hk/haskell.nix/archive/aa33b830162a5025fea684ab8659778ea871ba67.tar.gz",
        "url_template": "https://github.com/<owner>/<repo>/archive/<rev>.tar.gz"
    },
    "iohk-nix": {
        "branch": "master",
        "description": "nix scripts shared across projects",
        "homepage": null,
        "owner": "input-output-hk",
        "repo": "iohk-nix",
        "rev": "00788ac974a517846dba09bd5e095757011cb083",
        "sha256": "0lxffzd31a359d7j9q0vwaj6d5lq0ka5df6g0g30rm91sw7jkpnj",
        "type": "tarball",
        "url": "https://github.com/input-output-hk/iohk-nix/archive/00788ac974a517846dba09bd5e095757011cb083.tar.gz",
        "url_template": "https://github.com/<owner>/<repo>/archive/<rev>.tar.gz"
    },
    "niv": {
        "branch": "master",
        "description": "Easy dependency management for Nix projects",
        "homepage": "https://github.com/nmattia/niv",
        "owner": "nmattia",
        "repo": "niv",
        "rev": "98c74a80934123cb4c3bf3314567f67311eb711a",
        "sha256": "1w8n54hapd4x9f1am33icvngkqns7m3hl9yair38yqq08ffwg0kn",
        "type": "tarball",
        "url": "https://github.com/nmattia/niv/archive/98c74a80934123cb4c3bf3314567f67311eb711a.tar.gz",
        "url_template": "https://github.com/<owner>/<repo>/archive/<rev>.tar.gz"
    },
    "nixpkgs-19.03": {
        "branch": "release-19.03",
        "description": "Nix Packages collection",
        "homepage": null,
        "owner": "NixOS",
        "repo": "nixpkgs",
        "rev": "a8f81dc037a5977414a356dd068f2621b3c89b60",
        "sha256": "01z13axll5g5yl00lz9adr2jw2bs12g9skhbb1vxy8p7fjjbhhhm",
        "type": "tarball",
        "url": "https://github.com/NixOS/nixpkgs/archive/a8f81dc037a5977414a356dd068f2621b3c89b60.tar.gz",
        "url_template": "https://github.com/<owner>/<repo>/archive/<rev>.tar.gz"
    }
}
